{
  "teachers": [
    {
      "name": "Temurbek",
      "course": "Pythone",
      "id": "c092"
    },
    {
      "id": "72b4",
      "name": "Dilshod",
      "course": "React JS "
    },
    {
      "id": "d12f",
      "name": "Akmal",
      "course": "SMM"
    }
  ],
  "student": [
    {
      "name": "Dilshod",
      "age": "19",
      "number": "+998 91 108 44 55",
      "guruh": "N12",
      "course": "React JS ",
      "address": "Farg'ona viloyati",
      "id": "3f05"
    }
  ],
  "guruh": [
    {
      "name": "N12",
      "course": "Pythone",
      "id": "ad6f"
    },
    {
      "name": "a12",
      "course": "Front end",
      "id": "df41"
    }
  ],
  "course": [
    {
      "name": "Front end",
      "duration": 24,
      "price": 100,
      "id": "1159"
    },
    {
      "id": "106c",
      "name": "Back end",
      "duration": 25,
      "price": 120
    },
    {
      "id": "c2aa",
      "name": "Pythone",
      "duration": 20,
      "price": 90
    },
    {
      "id": "486f",
      "name": "React JS ",
      "duration": 7,
      "price": 100
    },
    {
      "id": "63c8",
      "name": "Dizain",
      "duration": 4,
      "price": 60
    }
  ]
}